logme/__init__.py
logme/__version__.py
logme/cli.py
logme/color_provider.py
logme/config.py
logme/exceptions.py
logme/providers.py
logme/utils.py
logme/cli/__init__.py
logme/cli/_cli.py
logme/cli/_cli_utils.py
logme/cli/_upgrade_utils.py
logme-1.3.2.dist-info/METADATA
logme-1.3.2.dist-info/RECORD
logme-1.3.2.dist-info/WHEEL
logme-1.3.2.dist-info/entry_points.txt
logme-1.3.2.dist-info/top_level.txt
