Metadata-Version: 2.1
Name: logme
Version: 1.3.2
Summary: package for easy logging
Home-page: https://github.com/BNMetrics/logme
Author: Luna Chen
Author-email: luna@bnmetrics.com
License: Apache 2.0
Keywords: logging,cli
Platform: UNKNOWN
Requires-Python: >=3.6
Requires-Dist: click
Requires-Dist: bnmutils
